{
  "lastUpdated": "2025년 07월 27일 08:36 KST",
  "news": {
    "investing": [
      {
        "title": "록히드 마틴, F-35 계약 6,170만 달러 확보",
        "link": "https://kr.investing.com/news/stock-market-news/article-93CH-1565008",
        "pubDate": "2025-07-26 18:53:53",
        "summary": "록히드 마틴, F-35 계약 6,170만 달러 확보"
      },
      {
        "title": "셀큐리티, 유방암 임상시험 결과 발표 앞두고 주가 급등",
        "link": "https://kr.investing.com/news/stock-market-news/article-93CH-1565007",
        "pubDate": "2025-07-26 18:47:28",
        "summary": "셀큐리티, 유방암 임상시험 결과 발표 앞두고 주가 급등"
      },
      {
        "title": "ATAI Life Sciences, CIAS 치료제 임상 실패 후 주가 급락",
        "link": "https://kr.investing.com/news/stock-market-news/article-93CH-1565005",
        "pubDate": "2025-07-26 18:28:42",
        "summary": "ATAI Life Sciences, CIAS 치료제 임상 실패 후 주가 급락"
      },
      {
        "title": "제록스 선순위 무담보 채권, S&P 글로벌 'B'로 강등",
        "link": "https://kr.investing.com/news/stock-market-news/article-93CH-1565002",
        "pubDate": "2025-07-26 18:05:10",
        "summary": "제록스 선순위 무담보 채권, S&P 글로벌 'B'로 강등"
      },
      {
        "title": "메타, 셩지아 자오를 슈퍼인텔리전스 랩 수석 과학자로 임명",
        "link": "https://kr.investing.com/news/stock-market-news/article-93CH-1565000",
        "pubDate": "2025-07-26 17:46:51",
        "summary": "메타, 셩지아 자오를 슈퍼인텔리전스 랩 수석 과학자로 임명"
      },
      {
        "title": "CrowdStrike Holdings, Moody's, 전망 '긍정적'으로 상향 조정",
        "link": "https://kr.investing.com/news/stock-market-news/article-93CH-1564998",
        "pubDate": "2025-07-26 17:20:04",
        "summary": "CrowdStrike Holdings, Moody's, 전망 '긍정적'으로 상향 조정"
      },
      {
        "title": "Procept Biorobotics, CEO 교체 발표 후 주가 하락",
        "link": "https://kr.investing.com/news/stock-market-news/article-93CH-1564997",
        "pubDate": "2025-07-26 17:15:05",
        "summary": "Procept Biorobotics, CEO 교체 발표 후 주가 하락"
      },
      {
        "title": "CrowdStrike Holdings, 무디스 전망 '긍정적'으로 상향",
        "link": "https://kr.investing.com/news/stock-market-news/article-93CH-1564996",
        "pubDate": "2025-07-26 17:10:12",
        "summary": "CrowdStrike Holdings, 무디스 전망 '긍정적'으로 상향"
      },
      {
        "title": "페이저듀티, 매각 가능성 보도에 주가 급등",
        "link": "https://kr.investing.com/news/stock-market-news/article-93CH-1564994",
        "pubDate": "2025-07-26 16:51:29",
        "summary": "페이저듀티, 매각 가능성 보도에 주가 급등"
      },
      {
        "title": "LVMH, Marc Jacobs 브랜드 매각 협상 중 - WSJ",
        "link": "https://kr.investing.com/news/stock-market-news/article-93CH-1564993",
        "pubDate": "2025-07-26 16:32:50",
        "summary": "LVMH, Marc Jacobs 브랜드 매각 협상 중 - WSJ"
      }
    ],
    "cnbc": [
      {
        "title": "Under Trump, Uncle Sam is becoming an active investor at a scale not seen outside war or major crises",
        "link": "https://www.cnbc.com/2025/07/26/under-trump-us-an-active-investor-at-scale-not-seen-outside-major-crises.html",
        "pubDate": "Sat, 26 Jul 2025 11:29:46 GMT",
        "summary": "The Trump administration has shown that it's willing to buy up stakes in publicly traded companies, a level of intervention that some say is unprecedented."
      },
      {
        "title": "EU chief to meet Trump in Scotland in push to avoid a transatlantic trade war",
        "link": "https://www.cnbc.com/2025/07/26/eu-chief-to-meet-trump-in-scotland-in-push-to-secure-a-us-trade-deal.html",
        "pubDate": "Sat, 26 Jul 2025 10:22:53 GMT",
        "summary": "\"I think we have a good 50/50 chance. That's a lot,\" Trump said."
      },
      {
        "title": "China releases AI action plan days after the U.S. as global tech race heats up",
        "link": "https://www.cnbc.com/2025/07/26/china-ai-action-plan.html",
        "pubDate": "Sat, 26 Jul 2025 13:54:40 GMT",
        "summary": "China on Saturday released a global action plan for artificial intelligence that called for international cooperation on tech development and regulation."
      },
      {
        "title": "Tesla investors are growing wary of Elon Musk's futuristic promises",
        "link": "https://www.cnbc.com/2025/07/26/tesla-investors-grow-wary-of-elon-musk-robotaxi-promises.html",
        "pubDate": "Sat, 26 Jul 2025 14:45:41 GMT",
        "summary": "Tesla shares plummeted as CEO Elon Musk's promises for robotaxis failed to excite investors following another disappointing earnings report."
      },
      {
        "title": "Trump's trade deals and tariffs are on the chopping block in court. What happens next",
        "link": "https://www.cnbc.com/2025/07/26/trump-tariffs-trade-lawsuits.html",
        "pubDate": "Sat, 26 Jul 2025 19:51:16 GMT",
        "summary": "Trump has recently announced preliminary trade deals with Japan and other countries, and many of his paused \"reciprocal\" tariffs are set to resume next month."
      },
      {
        "title": "Media trailblazer Tom Rogers changes ‘raging bull’ stance on Netflix, sees worrisome signs",
        "link": "https://www.cnbc.com/2025/07/26/netflix-raging-bull-changes-stance-what-worries-media-mogul-rogers.html",
        "pubDate": "Sat, 26 Jul 2025 15:22:33 GMT",
        "summary": "Former NBC Cable President Tom Rogers is raising concerns about Netflix amid a competitive streaming environment."
      },
      {
        "title": "Even many high-earning Americans don't feel wealthy. Here's why",
        "link": "https://www.cnbc.com/2025/07/26/henrys-why-high-earning-americans-do-not-feel-rich.html",
        "pubDate": "Sat, 26 Jul 2025 10:33:01 GMT",
        "summary": "Many high earners in the U.S. still feel broke. Between lifestyle creep, debt and social pressure, even $200,000 per year doesn't always buy peace of mind."
      },
      {
        "title": "The 10 worst U.S. states to retire—6 are in the South",
        "link": "https://www.cnbc.com/2025/07/26/worst-us-states-to-retire-bankrate.html",
        "pubDate": "Sat, 26 Jul 2025 13:00:01 GMT",
        "summary": "Factors like affordability and weather may make these states unattractive to retirees, but they could be right for you based on your personal preferences."
      },
      {
        "title": "CBS canceling Colbert begs the question: Are more late night shows next?",
        "link": "https://www.cnbc.com/2025/07/26/cbs-canceling-colbert-raises-late-night-questions.html",
        "pubDate": "Sat, 26 Jul 2025 11:00:01 GMT",
        "summary": "The cost of producing late night programs has risen as the media industry has been upended by streaming and shifting consumer habits."
      },
      {
        "title": "Are 2 to 3 cups of coffee a day too much? It's complicated, experts say: 'It's different for each person'",
        "link": "https://www.cnbc.com/2025/07/26/how-much-coffee-is-too-much-coffee-experts-weigh-in.html",
        "pubDate": "Sat, 26 Jul 2025 16:00:01 GMT",
        "summary": "Figuring out how much coffee is too much isn't straightforward. Experts explain why, and what you need to know about its benefits and risks."
      }
    ],
    "yahoo": [
      {
        "title": "General Dynamics Corporation (GD) Posted A Good Number, Says Jim Cramer",
        "link": "https://finance.yahoo.com/news/general-dynamics-corporation-gd-posted-231831185.html",
        "pubDate": "2025-07-26T23:18:31Z",
        "summary": "General Dynamics Corporation (GD) Posted A Good Number, Says Jim Cramer"
      },
      {
        "title": "Royal Caribbean Cruises Ltd. (RCL): The Downgrades Are A Chance To Buy, Says Jim Cramer",
        "link": "https://finance.yahoo.com/news/royal-caribbean-cruises-ltd-rcl-231735198.html",
        "pubDate": "2025-07-26T23:17:35Z",
        "summary": "Royal Caribbean Cruises Ltd. (RCL): The Downgrades Are A Chance To Buy, Says Jim Cramer"
      },
      {
        "title": "The Walt Disney Company (DIS)’s “Got A Good Cruise Business,” Says Jim Cramer",
        "link": "https://finance.yahoo.com/news/walt-disney-company-dis-got-231706127.html",
        "pubDate": "2025-07-26T23:17:06Z",
        "summary": "The Walt Disney Company (DIS)’s “Got A Good Cruise Business,” Says Jim Cramer"
      },
      {
        "title": "Fiserv, Inc. (FI): “That’s A High Flyer,” Says Jim Cramer",
        "link": "https://finance.yahoo.com/news/fiserv-inc-fi-high-flyer-231431305.html",
        "pubDate": "2025-07-26T23:14:31Z",
        "summary": "Fiserv, Inc. (FI): “That’s A High Flyer,” Says Jim Cramer"
      },
      {
        "title": "Hasbro, Inc. (HAS)’s Shares Dropped Because Of Chinese Materials, Says Jim Cramer",
        "link": "https://finance.yahoo.com/news/hasbro-inc-shares-dropped-because-231343535.html",
        "pubDate": "2025-07-26T23:13:43Z",
        "summary": "Hasbro, Inc. (HAS)’s Shares Dropped Because Of Chinese Materials, Says Jim Cramer"
      },
      {
        "title": "Microsoft Corporation (MSFT): “Will You Cut It Out?” Asks Jim Cramer",
        "link": "https://finance.yahoo.com/news/microsoft-corporation-msft-cut-asks-231259825.html",
        "pubDate": "2025-07-26T23:12:59Z",
        "summary": "Microsoft Corporation (MSFT): “Will You Cut It Out?” Asks Jim Cramer"
      },
      {
        "title": "Alphabet Inc. (GOOGL): “I Got It Wrong,” Admits Jim Cramer",
        "link": "https://finance.yahoo.com/news/alphabet-inc-googl-got-wrong-231235772.html",
        "pubDate": "2025-07-26T23:12:35Z",
        "summary": "Alphabet Inc. (GOOGL): “I Got It Wrong,” Admits Jim Cramer"
      },
      {
        "title": "The Bank of New York Mellon Corporation (BK)’s CEO Is Very Tech Proficient, Says Jim Cramer",
        "link": "https://finance.yahoo.com/news/bank-york-mellon-corporation-bk-231203708.html",
        "pubDate": "2025-07-26T23:12:03Z",
        "summary": "The Bank of New York Mellon Corporation (BK)’s CEO Is Very Tech Proficient, Says Jim Cramer"
      },
      {
        "title": "Circle Internet Group (CRCL) Might Not Have Anything Proprietary, Says Jim Cramer",
        "link": "https://finance.yahoo.com/news/circle-internet-group-crcl-might-231126835.html",
        "pubDate": "2025-07-26T23:11:26Z",
        "summary": "Circle Internet Group (CRCL) Might Not Have Anything Proprietary, Says Jim Cramer"
      },
      {
        "title": "BlackRock, Inc. (BLK)’s Gonna Win Big In Stablecoins, Says Jim Cramer",
        "link": "https://finance.yahoo.com/news/blackrock-inc-blk-gonna-win-231103651.html",
        "pubDate": "2025-07-26T23:11:03Z",
        "summary": "BlackRock, Inc. (BLK)’s Gonna Win Big In Stablecoins, Says Jim Cramer"
      }
    ]
  }
}