{
  "lastUpdated": "2025년 08월 06일 08:19 KST",
  "news": {
    "investing": [
      {
        "title": "CTW 케이맨, 주당 5달러로 IPO 가격 책정, 1,200만 달러 조달 예상",
        "link": "https://kr.investing.com/news/stock-market-news/article-432SI-1579955",
        "pubDate": "2025-08-05 21:52:09",
        "summary": "CTW 케이맨, 주당 5달러로 IPO 가격 책정, 1,200만 달러 조달 예상"
      },
      {
        "title": "웰스파고, AI 에이전트 확대를 위해 구글 클라우드와 파트너십 확대",
        "link": "https://kr.investing.com/news/stock-market-news/article-93CH-1579920",
        "pubDate": "2025-08-05 21:32:50",
        "summary": "웰스파고, AI 에이전트 확대를 위해 구글 클라우드와 파트너십 확대"
      },
      {
        "title": "장외 시간 주요 종목: AMD, Super Micro, 스냅, Match 등",
        "link": "https://kr.investing.com/news/stock-market-news/article-432SI-1579842",
        "pubDate": "2025-08-05 20:58:28",
        "summary": "장외 시간 주요 종목: AMD, Super Micro, 스냅, Match 등"
      },
      {
        "title": "연준 금리 인하 기대감에 TSX 급등",
        "link": "https://kr.investing.com/news/stock-market-news/article-1578575",
        "pubDate": "2025-08-05 20:44:06",
        "summary": "연준 금리 인하 기대감에 TSX 급등"
      },
      {
        "title": "아마존, IONQ 주식에 3,670만 달러 투자 공개, 주가 급등",
        "link": "https://kr.investing.com/news/stock-market-news/article-1579788",
        "pubDate": "2025-08-05 20:43:09",
        "summary": "아마존, IONQ 주식에 3,670만 달러 투자 공개, 주가 급등"
      },
      {
        "title": "트럼프 인도 관세 위협, 애플에 연간 100억 달러 비용 초래 가능 - 먼스터",
        "link": "https://kr.investing.com/news/stock-market-news/article-93CH-1579611",
        "pubDate": "2025-08-05 20:12:34",
        "summary": "트럼프 인도 관세 위협, 애플에 연간 100억 달러 비용 초래 가능 - 먼스터"
      },
      {
        "title": "Nvidia AI칩 불법 수출 혐의로 중국 국적자 Two 명 기소",
        "link": "https://kr.investing.com/news/stock-market-news/article-93CH-1579566",
        "pubDate": "2025-08-05 19:50:03",
        "summary": "Nvidia AI칩 불법 수출 혐의로 중국 국적자 Two 명 기소"
      },
      {
        "title": "BancFirst Corp., 보통주 발행 신청 제출",
        "link": "https://kr.investing.com/news/stock-market-news/article-432SI-1579564",
        "pubDate": "2025-08-05 19:47:08",
        "summary": "BancFirst Corp., 보통주 발행 신청 제출"
      },
      {
        "title": "타깃, 어려운 상황 속에서도 피치 신용등급 'A' 유지",
        "link": "https://kr.investing.com/news/stock-market-news/article-93CH-1579562",
        "pubDate": "2025-08-05 19:35:16",
        "summary": "타깃, 어려운 상황 속에서도 피치 신용등급 'A' 유지"
      },
      {
        "title": "엔비디아 AI칩 불법 수출 혐의로 중국인 Two 명 기소",
        "link": "https://kr.investing.com/news/stock-market-news/article-93CH-1579561",
        "pubDate": "2025-08-05 19:34:10",
        "summary": "엔비디아 AI칩 불법 수출 혐의로 중국인 Two 명 기소"
      }
    ],
    "cnbc": [
      {
        "title": "Super Micro shares plunge 15% on weak results, disappointing guidance",
        "link": "https://www.cnbc.com/2025/08/05/super-micro-smci-q4-earnings-report-2025.html",
        "pubDate": "Tue, 05 Aug 2025 21:37:29 GMT",
        "summary": "The server maker's business is still getting a big boost from artificial intelligence, but growth is slowing."
      },
      {
        "title": "AMD reports weaker-than-expected earnings even as revenue tops estimates",
        "link": "https://www.cnbc.com/2025/08/05/amd-earnings-report-2q-2025.html",
        "pubDate": "Tue, 05 Aug 2025 22:07:28 GMT",
        "summary": "AMD, which is second in the market for AI graphics processing units, is grappling with chip export controls."
      },
      {
        "title": "Snap shares plummet 15% after weak second-quarter revenue metric",
        "link": "https://www.cnbc.com/2025/08/05/snap-q2-earnings-report-2025.html",
        "pubDate": "Tue, 05 Aug 2025 22:02:16 GMT",
        "summary": "Snap shares tanked 15% Tuesday when it reported second-quarter earnings in which global average revenue per user missed expectations."
      },
      {
        "title": "Lucid softens full-year production forecast as EV maker misses second-quarter estimates",
        "link": "https://www.cnbc.com/2025/08/05/lucid-lcid-results-q2-2025.html",
        "pubDate": "Tue, 05 Aug 2025 21:56:56 GMT",
        "summary": "The electric vehicle maker now anticipates producing between 18,000 and 20,000 vehicles for the year after previously projecting a goal of 20,000."
      },
      {
        "title": "Yum Brands is cooking up more than fast food. It's preparing the industry's next CEOs",
        "link": "https://www.cnbc.com/2025/08/05/yum-brands-ceo-training-ground-restaurant-industry.html",
        "pubDate": "Tue, 05 Aug 2025 19:56:18 GMT",
        "summary": "CEOs like Brian Niccol, Kevin Hochman and Julie Felss Masino spent years at Yum Brands before leaving to lead other restaurant companies."
      },
      {
        "title": "Hinge Health stock pops 6% after first quarterly report since IPO",
        "link": "https://www.cnbc.com/2025/08/05/hinge-heatlh-hnge-stock-q2-2025-earnings.html",
        "pubDate": "Tue, 05 Aug 2025 20:49:54 GMT",
        "summary": "The company reported quarterly results for the first time since its debut on the New York Stock Exchange in May."
      },
      {
        "title": "Trump says pharma tariffs could eventually reach up to 250%",
        "link": "https://www.cnbc.com/2025/08/05/trump-says-pharma-tariffs-could-eventually-reach-up-to-250percent.html",
        "pubDate": "Tue, 05 Aug 2025 17:32:18 GMT",
        "summary": "Trump said he will initially impose a \"small tariff\" on pharmaceuticals, but then in a year to a year and a half, he will raise that rate to 150% and then 250%."
      },
      {
        "title": "Trump’s ‘big beautiful bill’ slashes this tax break for high earners in 2026",
        "link": "https://www.cnbc.com/2025/08/05/trump-big-beautiful-bill-charitable-deduction.html",
        "pubDate": "Tue, 05 Aug 2025 19:39:13 GMT",
        "summary": "President Donald Trump's \"big beautiful bill\" could reduce the deduction on charitable donations for higher earners in 2026. Here's what to know."
      },
      {
        "title": "Healthy Returns: Medicare, Medicaid will reportedly pilot covering obesity drugs – a potential win for drugmakers",
        "link": "https://www.cnbc.com/2025/08/05/healthy-returns-trump-administration-to-pilot-covering-obesity-drugs.html",
        "pubDate": "Tue, 05 Aug 2025 21:20:49 GMT",
        "summary": "The Trump administration is planning to pilot covering weight loss drugs. A longtime healthcare exec moves to a strategic advisory role at General Catalyst."
      },
      {
        "title": "Trump says JPMorgan Chase, Bank of America rejected him as a customer",
        "link": "https://www.cnbc.com/2025/08/05/trump-jpmorgan-chase-bank-of-america-rejected-bank-customer.html",
        "pubDate": "Tue, 05 Aug 2025 19:12:51 GMT",
        "summary": "President Donald Trump said Tuesday that the two largest U.S. banks rejected him as a bank customer, reviving claims of debanking against conservatives."
      }
    ],
    "yahoo": [
      {
        "title": "10 Cheap, Beautiful Places To Retire",
        "link": "https://finance.yahoo.com/news/15-cheap-beautiful-places-retire-143120191.html",
        "pubDate": "2025-08-05T08:03:35Z",
        "summary": "10 Cheap, Beautiful Places To Retire"
      },
      {
        "title": "Spotify Stock Bounces Back from Its Post-Earnings Plunge, But is SPOT Stock a Buy Right Now?",
        "link": "https://finance.yahoo.com/news/spotify-stock-bounces-back-post-150422097.html",
        "pubDate": "2025-08-04T15:04:22Z",
        "summary": "Spotify Stock Bounces Back from Its Post-Earnings Plunge, But is SPOT Stock a Buy Right Now?"
      },
      {
        "title": "Elon Musk Gets $23.7 Billion Stock Award From Tesla to Stay Focused",
        "link": "https://www.wsj.com/business/autos/tesla-approves-ceo-musk-pay-package-7c75a7bf?siteid=yhoof2&yptr=yahoo",
        "pubDate": "2025-08-04T15:16:00Z",
        "summary": "Elon Musk Gets $23.7 Billion Stock Award From Tesla to Stay Focused"
      },
      {
        "title": "Stocks Climb on Strength in Magnificent Seven Stocks and Chip Makers",
        "link": "https://finance.yahoo.com/news/stocks-climb-strength-magnificent-seven-151644287.html",
        "pubDate": "2025-08-04T15:16:44Z",
        "summary": "Stocks Climb on Strength in Magnificent Seven Stocks and Chip Makers"
      },
      {
        "title": "Amazon's slowing cloud growth could continue to drag on its stock",
        "link": "https://finance.yahoo.com/news/amazons-slowing-cloud-growth-could-continue-to-drag-on-its-stock-145741949.html",
        "pubDate": "2025-08-04T14:57:41Z",
        "summary": "Amazon's slowing cloud growth could continue to drag on its stock"
      },
      {
        "title": "Walmart’s Mexico CEO resigns and  Barrientos Pozo becomes interim",
        "link": "https://finance.yahoo.com/news/walmart-mexico-ceo-resigns-barrientos-150841382.html",
        "pubDate": "2025-08-04T15:08:41Z",
        "summary": "Walmart’s Mexico CEO resigns and  Barrientos Pozo becomes interim"
      },
      {
        "title": "Is Wall Street Bullish or Bearish on Norwegian Cruise Line Stock?",
        "link": "https://finance.yahoo.com/news/wall-street-bullish-bearish-norwegian-151859826.html",
        "pubDate": "2025-08-04T15:18:59Z",
        "summary": "Is Wall Street Bullish or Bearish on Norwegian Cruise Line Stock?"
      },
      {
        "title": "Owner of Price Chopper and Tops Friendly Markets explores sale, sources say",
        "link": "https://finance.yahoo.com/news/owner-price-chopper-tops-friendly-145454981.html",
        "pubDate": "2025-08-04T14:54:54Z",
        "summary": "Owner of Price Chopper and Tops Friendly Markets explores sale, sources say"
      },
      {
        "title": "Joby Aviation Aims for Commercial Flights with Deal for Blade Air’s Passenger Unit",
        "link": "https://www.wsj.com/business/airlines/joby-aviation-to-buy-blade-air-mobility-unit-for-up-to-125-million-b52c1b16?siteid=yhoof2&yptr=yahoo",
        "pubDate": "2025-08-04T14:55:00Z",
        "summary": "Joby Aviation Aims for Commercial Flights with Deal for Blade Air’s Passenger Unit"
      },
      {
        "title": "PetSmart Plans to Sell $4.7 Billion of Debt to Fund Refinancing",
        "link": "https://finance.yahoo.com/news/petsmart-plans-sell-4-7-150501232.html",
        "pubDate": "2025-08-04T15:05:01Z",
        "summary": "PetSmart Plans to Sell $4.7 Billion of Debt to Fund Refinancing"
      }
    ]
  }
}